{
	"geode": "4.6.1",
	"gd": {
		"win": "2.2074",
		"android": "2.2074",
		"mac": "2.2074",
		"ios": "2.2074"
	},
	"id": "alphalaneous.relog",
	"name": "Relog",
	"version": "v1.0.0",
	"developer": "Alphalaneous",
	"description": "Show console log in GD",
	"resources": {
        "fonts": {
            "Consolas": {
                "path": "resources/Consolas.ttf",
                "size": 55
            }
        },
		"sprites": [
			"resources/*.png"
		]
    },
	"early-load": true,
	"tags": ["developer", "utility", "offline", "enhancement"],
	    "links": {
        "homepage": "https://linktr.ee/Alphalaneous",
        "source": "https://github.com/Alphalaneous/Relog",
        "community": "https://discord.gg/Txn2CA5dHF"
    }
}
